troutpy/__init__.py
troutpy/_utils.py
troutpy/.ipynb_checkpoints/__init__-checkpoint.py
troutpy/pl/__init__.py
troutpy/pl/basic.py
troutpy/pl/colors.py
troutpy/pl/communication.py
troutpy/pl/factor_analysis.py
troutpy/pl/metric_analysis.py
troutpy/pl/plotting.py
troutpy/pl/scatter.py
troutpy/pl/source.py
troutpy/pl/.ipynb_checkpoints/__init__-checkpoint.py
troutpy/pl/.ipynb_checkpoints/basic-checkpoint.py
troutpy/pl/.ipynb_checkpoints/colors-checkpoint.py
troutpy/pl/.ipynb_checkpoints/communication-checkpoint.py
troutpy/pl/.ipynb_checkpoints/factor_analysis-checkpoint.py
troutpy/pl/.ipynb_checkpoints/metric_analysis-checkpoint.py
troutpy/pl/.ipynb_checkpoints/plotting-checkpoint.py
troutpy/pl/.ipynb_checkpoints/scatter-checkpoint.py
troutpy/pl/.ipynb_checkpoints/source-checkpoint.py
troutpy/pp/__init__.py
troutpy/pp/aggregate.py
troutpy/pp/compute.py
troutpy/pp/converter.py
troutpy/pp/format.py
troutpy/pp/.ipynb_checkpoints/__init__-checkpoint.py
troutpy/pp/.ipynb_checkpoints/aggregate-checkpoint.py
troutpy/pp/.ipynb_checkpoints/compute-checkpoint.py
troutpy/pp/.ipynb_checkpoints/converter-checkpoint.py
troutpy/pp/.ipynb_checkpoints/format-checkpoint.py
troutpy/read/__init__.py
troutpy/tl/__init__.py
troutpy/tl/estimate_density.py
troutpy/tl/factor_analysis.py
troutpy/tl/image_quantification.py
troutpy/tl/interactions.py
troutpy/tl/quantify_urna.py
troutpy/tl/segmentation_free.py
troutpy/tl/source_cell.py
troutpy/tl/target_cell.py
troutpy/tl/.ipynb_checkpoints/__init__-checkpoint.py
troutpy/tl/.ipynb_checkpoints/estimate_density-checkpoint.py
troutpy/tl/.ipynb_checkpoints/factor_analysis-checkpoint.py
troutpy/tl/.ipynb_checkpoints/image_quantification-checkpoint.py
troutpy/tl/.ipynb_checkpoints/interactions-checkpoint.py
troutpy/tl/.ipynb_checkpoints/quantify_urna-checkpoint.py
troutpy/tl/.ipynb_checkpoints/segmentation_free-checkpoint.py
troutpy/tl/.ipynb_checkpoints/source_cell-checkpoint.py
troutpy/tl/.ipynb_checkpoints/target_cell-checkpoint.py
troutpy-0.1.0.dist-info/METADATA
troutpy-0.1.0.dist-info/WHEEL
troutpy-0.1.0.dist-info/licenses/LICENSE
troutpy-0.1.0.dist-info/RECORD
