Metadata-Version: 2.4
Name: troutpy
Version: 0.1.0
Summary: Package for the analysis of transcripts outside segmented cells in python
Project-URL: Documentation, https://troutpy.readthedocs.io/
Project-URL: Homepage, https://github.com/sergiomarco25/troutpy
Project-URL: Source, https://github.com/sergiomarco25/troutpy
Author: Sergio Marco Salas
Maintainer-email: Sergio Marco Salas <sergio.salas@helmholtz-munich.de>
License: BSD 3-Clause License
License-File: LICENSE
Classifier: Programming Language :: Python :: 3 :: Only
Classifier: Programming Language :: Python :: 3.10
Classifier: Programming Language :: Python :: 3.11
Classifier: Programming Language :: Python :: 3.12
Classifier: Programming Language :: Python :: 3.13
Requires-Python: >=3.10
Requires-Dist: adjusttext>=1.3
Requires-Dist: dask==2024.11.2
Requires-Dist: docutils>=0.21.2
Requires-Dist: ipykernel>=6.29.5
Requires-Dist: ipython>=8.32
Requires-Dist: mpl-chord-diagram
Requires-Dist: points2regions
Requires-Dist: sainsc
Requires-Dist: scikit-learn>=1.6.1
Requires-Dist: seaborn
Requires-Dist: sopa[baysor,cellpose]
Requires-Dist: spatialdata
Requires-Dist: spatialdata-io
Requires-Dist: spatialdata-plot
Requires-Dist: squidpy>=1.6.2
Requires-Dist: statsmodels
Requires-Dist: tifffile>=2025.3.13
Provides-Extra: dev
Requires-Dist: pre-commit; extra == 'dev'
Requires-Dist: twine>=4.0.2; extra == 'dev'
Provides-Extra: doc
Requires-Dist: ipykernel; extra == 'doc'
Requires-Dist: ipython; extra == 'doc'
Requires-Dist: myst-nb>=1.1; extra == 'doc'
Requires-Dist: pandas; extra == 'doc'
Requires-Dist: setuptools; extra == 'doc'
Requires-Dist: sphinx-autodoc-typehints; extra == 'doc'
Requires-Dist: sphinx-book-theme>=1; extra == 'doc'
Requires-Dist: sphinx-copybutton; extra == 'doc'
Requires-Dist: sphinx-tabs; extra == 'doc'
Requires-Dist: sphinx>=4; extra == 'doc'
Requires-Dist: sphinxcontrib-bibtex>=1; extra == 'doc'
Requires-Dist: sphinxext-opengraph; extra == 'doc'
Provides-Extra: test
Requires-Dist: coverage; extra == 'test'
Requires-Dist: pytest; extra == 'test'
